<?xml version="1.0" encoding="UTF-8"?>
<Defs>

    <ThingDef ParentName="BaseWeapon_Bladelink">
        <defName>Mjolnir</defName>
        <label>Mjolnir</label>
        <description>Mjolnir, literally translated as Thor's hammer or thunder hammer, is the weapon of Thor. It was forged by a pair of dwarven craftsmen. During its forging, Loki transformed into a flying insect to interfere with the craftsmen,
             which is why Mjolnir's handle is exceptionally short.</description>
        <statBases>
            <DeteriorationRate>0</DeteriorationRate>
            <Flammability>0</Flammability>
            <MaxHitPoints>5000</MaxHitPoints>
            <WorkToMake>45000</WorkToMake>
            <!--<MarketValue>3000</MarketValue>-->
            <Mass>6</Mass>
        </statBases>
        <soundInteract>Interact_BladelinkZeusHammer</soundInteract>
        <meleeHitSound>MeleeHit_BladelinkZeusHammer</meleeHitSound>
        <smeltable>false</smeltable>
        <equippedAngleOffset>135</equippedAngleOffset>
        <costList>
            <Steel>600</Steel>
            <Obsidian>400</Obsidian>
        </costList>
        <graphicData>
            <graphicClass>Graphic_Single</graphicClass>
            <texPath>Weapons/Mjolnir</texPath>
        </graphicData>
        <weaponClasses>
            <li>Melee</li>
            <li>MeleeBlunt</li>
        </weaponClasses>
        <tools>
            <li>
                <label>handle</label>
                <capacities>
                    <li>Poke</li>
                </capacities>
                <power>22</power>
                <cooldownTime>1.0</cooldownTime>
                <extraMeleeDamages>
                    <li>
                        <def>LightningStrike</def>
                        <amount>10</amount>
                        <chance>1.0</chance>
                    </li>
                    <li>
                        <def>EMP</def>
                        <amount>75</amount>
                        <chance>1.0</chance>
                    </li>
                </extraMeleeDamages>
            </li>
            <li>
                <label>head</label>
                <capacities>
                    <li>Blunt</li>
                </capacities>
                <power>40</power>
                <cooldownTime>1.6</cooldownTime>
                <extraMeleeDamages>
                    <li>
                        <def>LightningStrike</def>
                        <amount>10</amount>
                        <chance>1.0</chance>
                    </li>
                    <li>
                        <def>EMP</def>
                        <amount>75</amount>
                        <chance>1.0</chance>
                    </li>
                </extraMeleeDamages>
            </li>
        </tools>
        <comps>
            <li Class="Artifact_Weapon_Arsenal.CompProperties_MoreAbility">
                <biocodeOnEquip>true</biocodeOnEquip>
                <AbilitieDefs>
                    <li>Bilskirnir</li>
                    <li>Thunderbolt</li>
                </AbilitieDefs>
            </li>
        </comps>
        <recipeMaker>
            <researchPrerequisite>Mjolnir</researchPrerequisite>
            <skillRequirements>
                <Crafting>12</Crafting>
            </skillRequirements>
            <displayPriority>500</displayPriority>
        </recipeMaker>
    </ThingDef>

</Defs>